agrippa/__init__.py
agrippa/__main__.py
agrippa/config.toml
agrippa/expr_parser.py
agrippa/parse.py
agrippa/utils.py
agrippa/onnx2torch/__init__.py
agrippa/onnx2torch/converter.py
agrippa/onnx2torch/onnx_graph.py
agrippa/onnx2torch/onnx_node.py
agrippa/onnx2torch/onnx_tensor.py
agrippa/onnx2torch/node_converters/__init__.py
agrippa/onnx2torch/node_converters/activations.py
agrippa/onnx2torch/node_converters/average_pool.py
agrippa/onnx2torch/node_converters/base_element_wise.py
agrippa/onnx2torch/node_converters/batch_norm.py
agrippa/onnx2torch/node_converters/binary_math_operations.py
agrippa/onnx2torch/node_converters/cast.py
agrippa/onnx2torch/node_converters/clip.py
agrippa/onnx2torch/node_converters/comparisons.py
agrippa/onnx2torch/node_converters/concat.py
agrippa/onnx2torch/node_converters/constant.py
agrippa/onnx2torch/node_converters/constant_of_shape.py
agrippa/onnx2torch/node_converters/conv.py
agrippa/onnx2torch/node_converters/cumsum.py
agrippa/onnx2torch/node_converters/dropout.py
agrippa/onnx2torch/node_converters/einsum.py
agrippa/onnx2torch/node_converters/expand.py
agrippa/onnx2torch/node_converters/flatten.py
agrippa/onnx2torch/node_converters/functions.py
agrippa/onnx2torch/node_converters/gather.py
agrippa/onnx2torch/node_converters/gemm.py
agrippa/onnx2torch/node_converters/global_average_pool.py
agrippa/onnx2torch/node_converters/identity.py
agrippa/onnx2torch/node_converters/logical.py
agrippa/onnx2torch/node_converters/lpnormalization.py
agrippa/onnx2torch/node_converters/lrn.py
agrippa/onnx2torch/node_converters/matmul.py
agrippa/onnx2torch/node_converters/max_pool.py
agrippa/onnx2torch/node_converters/mean.py
agrippa/onnx2torch/node_converters/min_max.py
agrippa/onnx2torch/node_converters/neg.py
agrippa/onnx2torch/node_converters/nms.py
agrippa/onnx2torch/node_converters/pad.py
agrippa/onnx2torch/node_converters/pow.py
agrippa/onnx2torch/node_converters/range.py
agrippa/onnx2torch/node_converters/reciprocal.py
agrippa-1.0.1.dist-info/LICENSE
agrippa-1.0.1.dist-info/METADATA
agrippa-1.0.1.dist-info/WHEEL
agrippa-1.0.1.dist-info/top_level.txt
agrippa-1.0.1.dist-info/RECORD
