Metadata-Version: 2.1
Name: agrippa
Version: 1.0.1
Summary: Making AI easier
Author-email: Gordon Kamer <gordon@agrippa.build>
License: The MIT License (MIT)
Keywords: ml,ai,artificial intelligence,neural networks
Requires-Python: >=3.8
License-File: LICENSE
Requires-Dist: numpy (<=1.23.4)
Requires-Dist: onnx (>=1.12.0)
Requires-Dist: torch (>=1.13.1)
Requires-Dist: torchvision (>=0.14.1)
